README.md
setup.py
async_oss/__init__.py
async_oss/api.py
async_oss/exceptions.py
async_oss/http.py
async_oss/iterators.py
async_oss/models.py
async_oss/utils.py
iaar_async_oss.egg-info/PKG-INFO
iaar_async_oss.egg-info/SOURCES.txt
iaar_async_oss.egg-info/dependency_links.txt
iaar_async_oss.egg-info/requires.txt
iaar_async_oss.egg-info/top_level.txt