Metadata-Version: 2.1
Name: iaar-async-oss
Version: 1.0.0
Summary: An asynchronous OSS library based on OSS2=2.15.0.
Author: Gie
Author-email: 593443714@qq.com
License: MIT
